{
  "summary": [
    {
      "body": "The thermostat in my kitchen water heater seems to have gone (water coming out at near boiling point) - can anyone recommend an electrician/plumber (whichever is more appropriate) to fix it?", 
      "date": "2007-07-08 20:39:00", 
      "id": 3485, 
      "responses": 3, 
      "subject": "electrician/plumber?", 
      "url": "http://www.barbicantalk.com/forum/viewtopic.php?f=2&t=3478"
    }, 
    {
      "body": "The water from my hot water cylinder is heated to a very high temperature. Yesterday a toddler got a nasty burn from the hot water tap, so I must now turn the thermostat to a lower setting. From a book I have this looks like quite a simple operation, but I would like to know if anyone has done it themselves and can confirm my impression.", 
      "date": "2007-04-09 12:10:00", 
      "id": 4371, 
      "responses": 3, 
      "subject": "Thermostat adjustment", 
      "url": "http://www.barbicantalk.com/forum/viewtopic.php?f=2&t=3213"
    }
  ]
}